ori_optimize/__init__.py
ori_optimize/envs/__init__.py
ori_optimize/envs/ori_optimize.py
ori_optimize-0.2.0.dist-info/METADATA
ori_optimize-0.2.0.dist-info/WHEEL
ori_optimize-0.2.0.dist-info/top_level.txt
ori_optimize-0.2.0.dist-info/RECORD
