Metadata-Version: 2.1
Name: ori-optimize
Version: 0.2.0
Summary: a environment that controls STL model rotate to reach the maximal 3D printing quality.
Requires-Dist: gym
Requires-Dist: numpy
